ophelia_spark/__init__.py
ophelia_spark/_info.py
ophelia_spark/_logger.py
ophelia_spark/_wrapper.py
ophelia_spark/evaluation/__init__.py
ophelia_spark/evaluation/metrics.py
ophelia_spark/functions.py
ophelia_spark/generic.py
ophelia_spark/ml/__init__.py
ophelia_spark/ml/feature_miner.py
ophelia_spark/ml/graphs/__init__.py
ophelia_spark/ml/optim/__init__.py
ophelia_spark/ml/optim/utils.py
ophelia_spark/ml/sampling/__init__.py
ophelia_spark/ml/sampling/synthetic_sample.py
ophelia_spark/ml/supervised/__init__.py
ophelia_spark/ml/supervised/classification.py
ophelia_spark/ml/supervised/regression.py
ophelia_spark/ml/unsupervised/__init__.py
ophelia_spark/ml/unsupervised/cluster.py
ophelia_spark/ml/unsupervised/feature.py
ophelia_spark/read/__init__.py
ophelia_spark/read/spark_read.py
ophelia_spark/session/__init__.py
ophelia_spark/session/spark.py
ophelia_spark/start.py
ophelia_spark/streaming/__init__.py
ophelia_spark/streaming/streaming_process.py
ophelia_spark/write/__init__.py
ophelia_spark/write/spark_write.py
ophelia_spark-0.1.3.dist-info/LICENSE
ophelia_spark-0.1.3.dist-info/METADATA
ophelia_spark-0.1.3.dist-info/WHEEL
ophelia_spark-0.1.3.dist-info/RECORD
