Metadata-Version: 2.1
Name: ophelia-spark
Version: 0.1.3
Summary: Ophelia is a spark miner AI engine that builds data mining & ml pipelines with PySpark.
Home-page: https://github.com/LuisFalva/ophelia
License: Free for non-commercial use
Keywords: ophelia-spark
Author: Luis Vargas
Author-email: falvaluis@gmail.com
Requires-Python: >=3.9,<3.12
Classifier: Development Status :: 1 - Planning
Classifier: Intended Audience :: Developers
Classifier: Intended Audience :: Financial and Insurance Industry
Classifier: Intended Audience :: Science/Research
Classifier: License :: Free for non-commercial use
Classifier: License :: Other/Proprietary License
Classifier: Programming Language :: Python :: 3
Classifier: Programming Language :: Python :: 3.9
Classifier: Programming Language :: Python :: 3.10
Classifier: Programming Language :: Python :: 3.11
Classifier: Programming Language :: Python :: 3.7
Classifier: Topic :: Office/Business :: Financial :: Investment
Classifier: Topic :: Scientific/Engineering :: Artificial Intelligence
Classifier: Topic :: Scientific/Engineering :: Information Analysis
Classifier: Topic :: Software Development :: Libraries
Classifier: Topic :: Software Development :: Libraries :: Python Modules
Requires-Dist: dask[dataframe] (>=2021.10.0)
Requires-Dist: numpy (>=1.21)
Requires-Dist: pandas (==2.2.2)
Requires-Dist: py4j (>=0.10.9)
Requires-Dist: pyarrow (==16.0.0)
Requires-Dist: pyhocon (==0.3.45)
Requires-Dist: pyspark (==3.2.2)
Requires-Dist: quadprog
Requires-Dist: scikit-learn (>=0.23.2)
Project-URL: Documentation, https://github.com/LuisFalva/ophelia
Project-URL: Repository, https://github.com/LuisFalva/ophelia
